<lifecycleMappingMetadata>
  <pluginExecutions>
    <pluginExecution>
      <pluginExecutionFilter>
        <groupId>org.jnario</groupId>
        <artifactId>jnario-maven-plugin</artifactId>
        <versionRange>[0.4.0,)</versionRange>
        <goals>
          <goal>testCompile</goal>
        </goals>
      </pluginExecutionFilter>
      <pluginExecutionFilter>
        <groupId>org.jnario</groupId>
        <artifactId>jnario-maven-report-plugin</artifactId>
        <versionRange>[0.4.0,)</versionRange>
        <goals>
          <goal>generate</goal>
        </goals>
      </pluginExecutionFilter>
      
      <action>
        <ignore />
      </action>
    </pluginExecution>
  </pluginExecutions>
</lifecycleMappingMetadata>